avadakedavra/__init__.py
avadakedavra-0.0.1.dist-info/METADATA
avadakedavra-0.0.1.dist-info/WHEEL
avadakedavra-0.0.1.dist-info/RECORD
