Metadata-Version: 2.1
Name: avadakedavra
Version: 0.0.1
Summary: GPT prompts.
Author: tom
Author-email: cyaeyz@gmail.com
Requires-Python: >=3.8,<4.0
Classifier: Programming Language :: Python :: 3
Classifier: Programming Language :: Python :: 3.8
Classifier: Programming Language :: Python :: 3.9
Classifier: Programming Language :: Python :: 3.10
Classifier: Programming Language :: Python :: 3.11
